{"pools":[{"conditions":[{"condition":"minecraft:survives_explosion"}],"entries":[{"functions":[{"function":"minecraft:copy_nbt","ops":[{"op":"replace","source":"componentSecurity.owner","target":"mekData.owner"},{"op":"replace","source":"componentSecurity.securityMode","target":"mekData.securityMode"},{"op":"replace","source":"componentUpgrade","target":"mekData.componentUpgrade"},{"op":"replace","source":"filters","target":"mekData.filters"},{"op":"replace","source":"auto","target":"mekData.auto"},{"op":"replace","source":"controlType","target":"mekData.controlType"}],"source":"block_entity"}],"name":"mekanism:qio_exporter","type":"minecraft:item"}],"rolls":1}],"type":"minecraft:block"}