{"ingredients":[{"component":"material","crop":"mysticalagriculture:certus_quartz","type":"mysticalagriculture:crop_component"},{"component":"essence","crop":"mysticalagriculture:certus_quartz","type":"mysticalagriculture:crop_component"},{"component":"material","crop":"mysticalagriculture:certus_quartz","type":"mysticalagriculture:crop_component"},{"component":"essence","crop":"mysticalagriculture:certus_quartz","type":"mysticalagriculture:crop_component"},{"component":"material","crop":"mysticalagriculture:certus_quartz","type":"mysticalagriculture:crop_component"},{"component":"essence","crop":"mysticalagriculture:certus_quartz","type":"mysticalagriculture:crop_component"},{"component":"material","crop":"mysticalagriculture:certus_quartz","type":"mysticalagriculture:crop_component"},{"component":"essence","crop":"mysticalagriculture:certus_quartz","type":"mysticalagriculture:crop_component"}],"input":{"component":"seed","crop":"mysticalagriculture:certus_quartz","type":"mysticalagriculture:crop_component"},"result":{"item":"mysticalagriculture:certus_quartz_seeds"},"type":"mysticalagriculture:infusion"}