{"ingredients":[{"component":"material","crop":"mysticalagriculture:nature","type":"mysticalagriculture:crop_component"},{"component":"essence","crop":"mysticalagriculture:nature","type":"mysticalagriculture:crop_component"},{"component":"material","crop":"mysticalagriculture:nature","type":"mysticalagriculture:crop_component"},{"component":"essence","crop":"mysticalagriculture:nature","type":"mysticalagriculture:crop_component"},{"component":"material","crop":"mysticalagriculture:nature","type":"mysticalagriculture:crop_component"},{"component":"essence","crop":"mysticalagriculture:nature","type":"mysticalagriculture:crop_component"},{"component":"material","crop":"mysticalagriculture:nature","type":"mysticalagriculture:crop_component"},{"component":"essence","crop":"mysticalagriculture:nature","type":"mysticalagriculture:crop_component"}],"input":{"component":"seed","crop":"mysticalagriculture:nature","type":"mysticalagriculture:crop_component"},"result":{"item":"mysticalagriculture:nature_seeds"},"type":"mysticalagriculture:infusion"}