{"mysticalagriculture:air":{"enabled":false},"mysticalagriculture:aluminum":{"enabled":false},"mysticalagriculture:apatite":{"enabled":false},"mysticalagriculture:brass":{"enabled":false},"mysticalagriculture:chrome":{"enabled":false},"mysticalagriculture:constantan":{"enabled":false},"mysticalagriculture:earth":{"enabled":false},"mysticalagriculture:electrum":{"enabled":false},"mysticalagriculture:end":{"ingredient":{"item":"minecraft:end_stone"}},"mysticalagriculture:enderium":{"enabled":false},"mysticalagriculture:fire":{"ingredient":{"item":"minecraft:lava_bucket"}},"mysticalagriculture:graphite":{"enabled":false},"mysticalagriculture:ice":{"tier":"mysticalagriculture:2"},"mysticalagriculture:invar":{"enabled":false},"mysticalagriculture:iridium":{"enabled":false},"mysticalagriculture:lumium":{"enabled":false},"mysticalagriculture:mithril":{"enabled":false},"mysticalagriculture:nether":{"ingredient":{"item":"minecraft:netherrack"}},"mysticalagriculture:nickel":{"enabled":false},"mysticalagriculture:platinum":{"enabled":false},"mysticalagriculture:rubber":{"enabled":false},"mysticalagriculture:saltpeter":{"enabled":false},"mysticalagriculture:signalum":{"enabled":false},"mysticalagriculture:silicon":{"enabled":false},"mysticalagriculture:silver":{"enabled":false},"mysticalagriculture:titanium":{"enabled":false},"mysticalagriculture:tungsten":{"enabled":false},"mysticalagriculture:water":{"ingredient":{"item":"minecraft:water_bucket"}},"mysticalagriculture:zinc":{"enabled":false}}